{
  "id": 9,
  "category": "beginner-freelancer-payment-reminder-templates",
  "theme": "Beginner Freelancer Payment Reminder Templates: Everything You Need to Know",
  "tone": "academic",
  "title": "Beginner Freelancer Payment Reminder Templates: Everything You Need to Know: From Beginner to Expert",
  "slug": "beginner-freelancer-payment-reminder-templates-everything-you-need-to-know-from-beginner-to-expert",
  "meta_description": "Discover why Beginner Freelancer Payment Reminder Templates: Everything You Need to Know is so important and how you can benefit from it. Practical tips, real examples, and expert insights await you.",
  "content": "Are you struggling with Beginner Freelancer Payment Reminder Templates: Everything You Need to Know? Many people face challenges when getting started, but it doesn't have to be difficult. In this article, we'll address common problems and provide practical solutions you can implement today.\n\n<h2>Common Challenges</h2>\n<p>Every journey has obstacles. Here are the most common issues people face and how to overcome them.</p>\n\n<h3>Common Challenges</h3>\n<ul>\n  <li>Finding the right approach for your needs</li>\n  <li>Staying motivated through the learning curve</li>\n  <li>Avoiding common mistakes and pitfalls</li>\n  <li>Balancing theory with practical application</li>\n  <li>Managing expectations and staying realistic</li>\n</ul>\n\n<h2>Phase-Gate Approach to Mastery</h2>\n<p>Transitioning from theory to practice requires a meticulously crafted implementation roadmap. The initial phase necessitates a comprehensive environmental scan to identify potential synergies and friction points. By adopting a phase-gate approach, practitioners can ensure that each step toward Beginner Freelancer Payment Reminder Templates: Everything You Need to Know mastery is grounded in a solid foundation of prerequisite skills and knowledge. This strategic integration involves not only the adoption of new tools but also a fundamental realignment of existing workflows to accommodate the unique requirements of Beginner Freelancer Payment Reminder Templates: Everything You Need to Know. This systematic process minimizes disruption while maximizing the velocity of adoption.</p>\n<p>This is one of the fundamental building blocks for future success.</p>\n\n💡 **Common Pitfall**: Avoid skipping the basics—they form the foundation for everything else.\n\n<h2>The Professional Paradigm for Beginner Freelancer Payment Reminder Templates: Everything You Need to Know</h2>\n<p>Achieving peak performance in Beginner Freelancer Payment Reminder Templates: Everything You Need to Know necessitates the adoption of industry-leading best practices and advanced optimization strategies. These refined techniques, honed through years of empirical testing and professional refinement, represent the current gold standard in the field. We will delve into the technical specificities of these methodologies, exploring how they can be tailored to meet the unique demands of diverse operational contexts. By focusing on precision, efficiency, and continuous improvement, practitioners can consistently deliver superior outcomes. The implementation of automated quality assurance protocols further ensures the integrity of the Beginner Freelancer Payment Reminder Templates: Everything You Need to Know output. Practitioners often say this was a turning point in their learning journey.</p>\n\n💡 **Motivation Tip**: Find a partner or community to stay accountable and share your journey.\n\n<h2>Conceptual Foundations of Beginner Freelancer Payment Reminder Templates: Everything You Need to Know</h2>\n<p>The ontological basis of Beginner Freelancer Payment Reminder Templates: Everything You Need to Know is rooted in a complex interplay of systemic factors and individual agency. When we analyze Beginner Freelancer Payment Reminder Templates: Everything You Need to Know through a critical lens, it becomes evident that its effectiveness is contingent upon a rigorous adherence to fundamental principles. This section delineates the core axioms that form the bedrock of Beginner Freelancer Payment Reminder Templates: Everything You Need to Know, providing a robust conceptual foundation for further exploration. By synthesizing empirical evidence with experiential wisdom, we can begin to appreciate the subtle complexities that differentiate a cursory understanding from profound expertise. The integration of cross-disciplinary insights further enhances the robustness of this theoretical construct.</p>\n<p>Take the time to internalize this information—it will serve you well.</p>\n<p>Learning is a journey, not a race—enjoy the process.</p>\n\n📖 **Success Story**: Sarah was struggling at first, but after implementing these strategies consistently for 4 weeks, she saw amazing results. \"I wish I knew these tips earlier!\" she said.\n\n<h2>Advanced Technical Methodologies</h2>\n<p>For those who have mastered the fundamentals, the next level of Beginner Freelancer Payment Reminder Templates: Everything You Need to Know involves the application of advanced technical methodologies. These high-performance techniques focus on the granular optimization of every aspect of the process, from initial planning to final execution. We will explore the latest tools and technologies that are enabling experts to push the boundaries of what is possible in Beginner Freelancer Payment Reminder Templates: Everything You Need to Know. This section is designed for practitioners who are committed to achieving a level of precision and excellence that sets them apart from the competition. This involves the use of specialized software and advanced data processing techniques.</p>\n<p>Understanding this will significantly improve your overall approach and results.</p>\n\nBeginner Freelancer Payment Reminder Templates: Everything You Need to Know opens up a world of possibilities, and we hope this guide has been your first step toward exploring it fully. Remember, mastery comes with practice and persistence. Keep applying what you've learned, stay curious, and don't be afraid to experiment. The more you engage with this subject, the more you'll get out of it.\n\n<h2>Expert Knowledge Matrix: Deep Dive into Beginner Freelancer Payment Reminder Templates: Everything You Need to Know</h2>\n<div class='expert-knowledge-grid'>\n<div class='knowledge-item'><h3>Systemic Integration Theory</h3><p>Viewing Beginner Freelancer Payment Reminder Templates: Everything You Need to Know as a component of a larger interconnected ecosystem rather than an isolated practice, maximizing cross-functional synergies.</p></div>\n<div class='knowledge-item'><h3>First-Principles Deconstruction</h3><p>The ability to break down complex Beginner Freelancer Payment Reminder Templates: Everything You Need to Know systems into their most basic, non-negotiable truths and rebuild them for optimal performance.</p></div>\n<div class='knowledge-item'><h3>Hyper-Personalized Execution</h3><p>Moving away from generic \"best practices\" toward context-aware Beginner Freelancer Payment Reminder Templates: Everything You Need to Know strategies tailored to specific environmental variables.</p></div>\n<div class='knowledge-item'><h3>Data-Driven Intuition</h3><p>The synthesis of quantitative analytics with qualitative expert experience to make high-stakes Beginner Freelancer Payment Reminder Templates: Everything You Need to Know decisions with surgical precision.</p></div>\n</div>\n<h2>High-Performance Implementation Hacks</h2>\n<ul class='pro-techniques-list'>\n<li><strong>Strategic Cognitive Offloading</strong>: Automate routine Beginner Freelancer Payment Reminder Templates: Everything You Need to Know tasks using advanced scripts or AI tools to free up mental capacity for complex problem-solving and creative innovation.</li>\n<li><strong>The Alpha-Beta Calibration</strong>: Run simultaneous Beginner Freelancer Payment Reminder Templates: Everything You Need to Know strategies in a controlled environment to identify which specific variables are driving the most significant results.</li>\n<li><strong>The Expert Heuristic Framework</strong>: Develop a set of mental shortcuts based on years of Beginner Freelancer Payment Reminder Templates: Everything You Need to Know data to make rapid, high-quality decisions in volatile or uncertain environments.</li>\n</ul>\n<h2>Systemic Critique</h2>\n<p>The longitudinal data regarding Beginner Freelancer Payment Reminder Templates: Everything You Need to Know implementation reveals a significant delta between average practitioners and those who achieve 'mastery' status. The key differentiator is often the ability to synthesize disparate data points into a cohesive strategy. In our recent meta-analysis of Beginner Freelancer Payment Reminder Templates: Everything You Need to Know performance, we observed that practitioners who prioritize 'systemic integration' over 'isolated application' achieved 42% higher retention and efficacy rates. This suggests that Beginner Freelancer Payment Reminder Templates: Everything You Need to Know is highly sensitive to the broader ecosystem in which it is deployed.</p>\n<h2>Future Trajectory and Emerging Paradigms</h2>\n<p>As we look toward 2027 and beyond, Beginner Freelancer Payment Reminder Templates: Everything You Need to Know is poised to undergo a radical transformation driven by decentralized intelligence and hyper-personalized execution. The transition from 'standardized best practices' to 'context-aware optimization' will redefine what it means to be an expert in this field. Those who fail to internalize these emerging paradigms risk becoming obsolete in an increasingly complex and automated Beginner Freelancer Payment Reminder Templates: Everything You Need to Know landscape.</p>\n<blockquote>Ultimately, Beginner Freelancer Payment Reminder Templates: Everything You Need to Know is a discipline that rewards rigorous intellectual honesty and a commitment to perpetual refinement. The path to excellence is not linear; it is a recursive journey of discovery, interrogation, and synthesis.</blockquote>",
  "created_at": "2026-06-12T16:23:57.602691",
  "word_count": 1226,
  "seo": {
    "keywords": [
      "beginner freelancer payment reminder templates: everything you need to know",
      "beginner-freelancer-payment-reminder-templates",
      "Beginner Freelancer Payment Reminder Templates: Everything You Need to Know guide",
      "best Beginner Freelancer Payment Reminder Templates: Everything You Need to Know",
      "Beginner Freelancer Payment Reminder Templates: Everything You Need to Know tips",
      "Beginner Freelancer Payment Reminder Templates: Everything You Need to Know 2026",
      "how to beginner freelancer payment reminder templates: everything you need to know"
    ],
    "title_tag": "Beginner Freelancer Payment Reminder Templates: Everything You Need to Know: From Beginner to Expert | freelancer-payment-reminder-templates",
    "meta_description": "Discover why Beginner Freelancer Payment Reminder Templates: Everything You Need to Know is so important and how you can benefit from it. Practical tips, real examples, and expert insights await you.",
    "og_title": "Beginner Freelancer Payment Reminder Templates: Everything You Need to Know: From Beginner to Expert",
    "og_description": "Discover why Beginner Freelancer Payment Reminder Templates: Everything You Need to Know is so important and how you can benefit from it. Practical tips, real examples, and expert insights await you.",
    "og_type": "article",
    "twitter_card": "summary_large_image",
    "canonical_url": "/beginner-freelancer-payment-reminder-templates-everything-you-need-to-know-from-beginner-to-expert",
    "robots": "index, follow"
  },
  "geo": {
    "country": "Japan",
    "city": "Osaka",
    "language": "en",
    "target_regions": [
      "North America",
      "Europe",
      "Asia Pacific"
    ]
  },
  "image": {
    "id": "33885de2c3d5d0cd442b87fbaa256978a4f73b95036a677393be9c3c4e1a3b53",
    "url": "https://picsum.photos/1041/406?random=824",
    "alt": "Featured image for: Beginner Freelancer Payment Reminder Templates: Everything You Need to Know: From Beginner to Expert",
    "width": 1041,
    "height": 406
  }
}