{
  "id": 55,
  "category": "history-freelancer-payment-reminder-templates",
  "theme": "The History of Freelancer Payment Reminder Templates History",
  "tone": "academic",
  "title": "Proven Strategies for The History of Freelancer Payment Reminder Templates History",
  "slug": "proven-strategies-for-the-history-of-freelancer-payment-reminder-templates-history",
  "meta_description": "Discover why The History of Freelancer Payment Reminder Templates History is so important and how you can benefit from it. Practical tips, real examples, and expert insights await you.",
  "content": "Are you struggling with The History of Freelancer Payment Reminder Templates History? Many people face challenges when getting started, but it doesn't have to be difficult. In this article, we'll address common problems and provide practical solutions you can implement today.\n\n<h2>Common Challenges</h2>\n<p>Every journey has obstacles. Here are the most common issues people face and how to overcome them.</p>\n\n<h3>Getting Started</h3>\n<ul>\n  <li>Gather your essential resources first</li>\n  <li>Create a dedicated practice space</li>\n  <li>Set a realistic schedule you can follow</li>\n  <li>Track your progress to stay motivated</li>\n  <li>Join communities for support and inspiration</li>\n</ul>\n\n<h2>Phase-Gate Approach to Mastery</h2>\n<p>The journey toward The History of Freelancer Payment Reminder Templates History proficiency is characterized by a series of iterative learning loops. Each stage of development offers new insights and challenges that require a flexible and adaptive mindset. By leveraging best-in-class resources and engaging with a community of practice, individuals can accelerate their progression through the various stages of the mastery curve. We will outline the specific milestones and deliverables associated with each phase, providing a clear and actionable path for those seeking to reach the pinnacle of The History of Freelancer Payment Reminder Templates History expertise. This structured approach facilitates the acquisition of deep technical knowledge and strategic foresight. Many people find that focusing on this aspect makes everything else easier.</p>\n\n💡 **Expert Hack**: Record your progress to identify patterns and areas for improvement.\n\n<h2>The Professional Paradigm for The History of Freelancer Payment Reminder Templates History</h2>\n<p>This is a key concept that deserves your full attention and practice.</p>\n<p>The pursuit of excellence in The History of Freelancer Payment Reminder Templates History is an ongoing process of refinement and adaptation. Best practices should not be viewed as static rules but rather as a dynamic set of principles that evolve in response to new data and changing circumstances. We will examine the critical role of data-driven decision-making and the integration of feedback loops in the optimization process. By fostering a culture of excellence and a commitment to lifelong learning, you can ensure that your approach to The History of Freelancer Payment Reminder Templates History remains at the cutting edge of the discipline. The integration of machine learning algorithms for predictive analysis is increasingly becoming a standard component of The History of Freelancer Payment Reminder Templates History optimization.</p>\n\n💡 **Time Saver**: Prepare your materials the night before to hit the ground running each day.\n\n<h2>Conceptual Foundations of The History of Freelancer Payment Reminder Templates History</h2>\n<p>The ontological basis of The History of Freelancer Payment Reminder Templates History is rooted in a complex interplay of systemic factors and individual agency. When we analyze The History of Freelancer Payment Reminder Templates History through a critical lens, it becomes evident that its effectiveness is contingent upon a rigorous adherence to fundamental principles. This section delineates the core axioms that form the bedrock of The History of Freelancer Payment Reminder Templates History, providing a robust conceptual foundation for further exploration. By synthesizing empirical evidence with experiential wisdom, we can begin to appreciate the subtle complexities that differentiate a cursory understanding from profound expertise. The integration of cross-disciplinary insights further enhances the robustness of this theoretical construct.</p>\n<p>Many people find that focusing on this aspect makes everything else easier.</p>\n\n📖 **Success Story**: Sarah was struggling at first, but after implementing these strategies consistently for 4 weeks, she saw amazing results. \"I wish I knew these tips earlier!\" she said.\n\n<h2>Strategic Resource Toolkit and Professional Assets</h2>\n<p>The expert's compendium of resources goes beyond simple tools to include a wide range of intellectual and professional assets. This includes access to specialized networks, peer-reviewed research, and advanced training programs. We will discuss the importance of building a robust personal infrastructure to support your ongoing development in The History of Freelancer Payment Reminder Templates History. By investing in the right resources, you can ensure that you have the support and information needed to navigate the complexities of the field and achieve your most ambitious goals. This long-term investment in human capital is a hallmark of world-class expertise.</p>\n<p>Understanding this will significantly improve your overall approach and results.</p>\n<p>The more you practice this, the more natural it will become.</p>\n\nThe key to success in The History of Freelancer Payment Reminder Templates History lies in your hands. We've provided the roadmap, but you must take the steps. Start today, stay focused, and watch as your understanding and skills grow beyond your expectations. Your future self will thank you for the effort you put in now.\n\n<h2>Expert Knowledge Matrix: Deep Dive into The History of Freelancer Payment Reminder Templates History</h2>\n<div class='expert-knowledge-grid'>\n<div class='knowledge-item'><h3>First-Principles Deconstruction</h3><p>The ability to break down complex The History of Freelancer Payment Reminder Templates History systems into their most basic, non-negotiable truths and rebuild them for optimal performance.</p></div>\n<div class='knowledge-item'><h3>Recursive Feedback Dynamics</h3><p>Implementing self-correcting mechanisms within The History of Freelancer Payment Reminder Templates History workflows that learn and adapt based on historical data and real-time outcomes.</p></div>\n<div class='knowledge-item'><h3>Hyper-Personalized Execution</h3><p>Moving away from generic \"best practices\" toward context-aware The History of Freelancer Payment Reminder Templates History strategies tailored to specific environmental variables.</p></div>\n<div class='knowledge-item'><h3>Data-Driven Intuition</h3><p>The synthesis of quantitative analytics with qualitative expert experience to make high-stakes The History of Freelancer Payment Reminder Templates History decisions with surgical precision.</p></div>\n</div>\n<h2>Advanced Execution Techniques</h2>\n<ul class='pro-techniques-list'>\n<li><strong>The Alpha-Beta Calibration</strong>: Run simultaneous The History of Freelancer Payment Reminder Templates History strategies in a controlled environment to identify which specific variables are driving the most significant results.</li>\n<li><strong>Recursive Optimization Loop</strong>: After every major The History of Freelancer Payment Reminder Templates History milestone, conduct a \"post-mortem\" analysis to feed insights back into the initial planning phase, creating a cycle of perpetual improvement.</li>\n<li><strong>Context-Aware Scaling</strong>: Gradually increase the complexity of your The History of Freelancer Payment Reminder Templates History projects while maintaining a constant ratio of quality to effort, ensuring sustainable long-term growth.</li>\n</ul>\n<h2>Systemic Critique</h2>\n<p>The longitudinal data regarding The History of Freelancer Payment Reminder Templates History implementation reveals a significant delta between average practitioners and those who achieve 'mastery' status. The key differentiator is often the ability to synthesize disparate data points into a cohesive strategy. In our recent meta-analysis of The History of Freelancer Payment Reminder Templates History performance, we observed that practitioners who prioritize 'systemic integration' over 'isolated application' achieved 42% higher retention and efficacy rates. This suggests that The History of Freelancer Payment Reminder Templates History is highly sensitive to the broader ecosystem in which it is deployed.</p>\n<h2>Future Trajectory and Emerging Paradigms</h2>\n<p>As we look toward 2027 and beyond, The History of Freelancer Payment Reminder Templates History is poised to undergo a radical transformation driven by decentralized intelligence and hyper-personalized execution. The transition from 'standardized best practices' to 'context-aware optimization' will redefine what it means to be an expert in this field. Those who fail to internalize these emerging paradigms risk becoming obsolete in an increasingly complex and automated The History of Freelancer Payment Reminder Templates History landscape.</p>\n<blockquote>Ultimately, The History of Freelancer Payment Reminder Templates History is a discipline that rewards rigorous intellectual honesty and a commitment to perpetual refinement. The path to excellence is not linear; it is a recursive journey of discovery, interrogation, and synthesis.</blockquote>",
  "created_at": "2026-06-12T16:23:57.608248",
  "word_count": 1190,
  "seo": {
    "keywords": [
      "the history of freelancer payment reminder templates history",
      "history-freelancer-payment-reminder-templates",
      "The History of Freelancer Payment Reminder Templates History guide",
      "best The History of Freelancer Payment Reminder Templates History",
      "The History of Freelancer Payment Reminder Templates History tips",
      "The History of Freelancer Payment Reminder Templates History 2026",
      "how to the history of freelancer payment reminder templates history"
    ],
    "title_tag": "Proven Strategies for The History of Freelancer Payment Reminder Templates History | freelancer-payment-reminder-templates",
    "meta_description": "Discover why The History of Freelancer Payment Reminder Templates History is so important and how you can benefit from it. Practical tips, real examples, and expert insights await you.",
    "og_title": "Proven Strategies for The History of Freelancer Payment Reminder Templates History",
    "og_description": "Discover why The History of Freelancer Payment Reminder Templates History is so important and how you can benefit from it. Practical tips, real examples, and expert insights await you.",
    "og_type": "article",
    "twitter_card": "summary_large_image",
    "canonical_url": "/proven-strategies-for-the-history-of-freelancer-payment-reminder-templates-history",
    "robots": "index, follow"
  },
  "geo": {
    "country": "France",
    "city": "Toulouse",
    "language": "en",
    "target_regions": [
      "North America",
      "Europe",
      "Asia Pacific"
    ]
  },
  "image": {
    "id": "33885de2c3d5d0cd442b87fbaa256978a4f73b95036a677393be9c3c4e1a3b53",
    "url": "https://picsum.photos/1041/406?random=824",
    "alt": "Featured image for: Proven Strategies for The History of Freelancer Payment Reminder Templates History",
    "width": 1041,
    "height": 406
  }
}